viperD/__init__.py
viperD/command_line.py
viperD/dir_file_names.pkl
viperD/utils.py
viperD/templates/.DS_Store
viperD/templates/Dockers_file/.DS_Store
viperD/templates/Dockers_file/app/Dockerfile
viperD/templates/Dockers_file/app_backup/Dockerfile
viperD/templates/Dockers_file/app_initiatory/Dockerfile
viperD/templates/Dockers_file/nginx/Dockerfile
viperD/templates/Dockers_file/nginx/nginx.conf
viperD/templates/Dockers_file/nginx/project.conf
viperD/templates/Dockers_file/requirements/requirements.py
viperD/templates/Dockers_file/requirements/requirements.txt
viperD/templates/Dockers_file/ubuntu_image/Dockerfile
viperD/templates/code_mount/__init__.py
viperD/templates/data_mount/__init__.py
viperD/templates/execute/.DS_Store
viperD/templates/execute/readme.md
viperD/templates/execute/Linux/build_images.sh
viperD/templates/execute/Linux/build_images_initiatory.sh
viperD/templates/execute/Linux/run_docker.sh
viperD/templates/execute/Linux/run_docker_dev host.sh
viperD/templates/execute/Linux/run_docker_dev.sh
viperD/templates/execute/Windows/build_images.bat
viperD/templates/execute/Windows/build_images_initiatory.bat
viperD/templates/execute/Windows/run_docker.bat
viperD/templates/execute/Windows/run_docker_dev.bat
viperD-0.2.1.dist-info/LICENSE
viperD-0.2.1.dist-info/METADATA
viperD-0.2.1.dist-info/WHEEL
viperD-0.2.1.dist-info/entry_points.txt
viperD-0.2.1.dist-info/top_level.txt
viperD-0.2.1.dist-info/zip-safe
viperD-0.2.1.dist-info/RECORD
